geventmp/LICENSE
geventmp/__init__.py
geventmp/monkey.py
geventmp/_mp/__init__.py
geventmp/_mp/3/__init__.py
geventmp/_mp/3/_mp_connection.py
geventmp/_mp/3/_mp_forkserver.py
geventmp/_mp/3/_mp_popen_fork.py
geventmp/_mp/3/_mp_popen_forkserver.py
geventmp/_mp/3/_mp_popen_spawn_posix.py
geventmp/_mp/3/_mp_resource_tracker.py
geventmp/_mp/3/_mp_sem_tracker.py
geventmp/_mp/3/_mp_spawn.py
geventmp/_mp/3/_mp_synchronize.py
geventmp/_mp/3/_mp_util.py
geventmp-0.0.10.dist-info/METADATA
geventmp-0.0.10.dist-info/WHEEL
geventmp-0.0.10.dist-info/entry_points.txt
geventmp-0.0.10.dist-info/namespace_packages.txt
geventmp-0.0.10.dist-info/top_level.txt
geventmp-0.0.10.dist-info/zip-safe
geventmp-0.0.10.dist-info/RECORD
