Metadata-Version: 2.4
Name: geventmp
Version: 0.0.10
Summary: Multiprocessing Gevent Extension
Home-page: https://github.com/karellen/geventmp
Author: Karellen, Inc.
Author-email: supervisor@karellen.co
Maintainer: Arcadiy Ivanov
Maintainer-email: arcadiy@ivanov.biz
License: Apache-2.0
Project-URL: Bug Tracker, https://github.com/karellen/geventmp/issues
Project-URL: Documentation, https://github.com/karellen/geventmp/
Project-URL: Source Code, https://github.com/karellen/geventmp/
Keywords: gevent multiprocessing mp monkey
Classifier: Programming Language :: Python :: 3.9
Classifier: Programming Language :: Python :: 3.10
Classifier: Programming Language :: Python :: 3.11
Classifier: Programming Language :: Python :: 3.12
Classifier: Programming Language :: Python :: 3.13
Classifier: Programming Language :: Python :: 3.14
Classifier: Programming Language :: Python :: Implementation :: CPython
Classifier: Programming Language :: Python :: Implementation :: PyPy
Classifier: Operating System :: MacOS :: MacOS X
Classifier: Operating System :: POSIX
Classifier: Topic :: Internet
Classifier: Topic :: Software Development :: Libraries :: Python Modules
Classifier: Intended Audience :: Developers
Classifier: Development Status :: 4 - Beta
Requires-Python: >=3.9
Requires-Dist: gevent>=25.8.2
Dynamic: author
Dynamic: author-email
Dynamic: classifier
Dynamic: description
Dynamic: description-content-type
Dynamic: home-page
Dynamic: keywords
Dynamic: license
Dynamic: maintainer
Dynamic: maintainer-email
Dynamic: project-url
Dynamic: requires-dist
Dynamic: requires-python
Dynamic: summary
